lightning_proxies/__init__.py
lightning_proxies/api.py
lightning_proxies/exceptions.py
lightning_proxies/validators.py
tests/__init__.py
tests/test_api.py
lightning_proxies-0.1.1.dist-info/LICENSE
lightning_proxies-0.1.1.dist-info/METADATA
lightning_proxies-0.1.1.dist-info/WHEEL
lightning_proxies-0.1.1.dist-info/top_level.txt
lightning_proxies-0.1.1.dist-info/RECORD
