Metadata-Version: 2.1
Name: lightning-proxies
Version: 0.1.1
Summary: A Python client for managing Lightning Proxies API
Home-page: https://github.com/sandersbasket/LightningProxiesAPI
Author: sanders basket
Classifier: Programming Language :: Python :: 3
Classifier: License :: OSI Approved :: MIT License
Classifier: Operating System :: OS Independent
Requires-Python: >=3.6
License-File: LICENSE
Requires-Dist: requests >=2.25.1
Provides-Extra: dev
Requires-Dist: pytest >=6.0 ; extra == 'dev'
Requires-Dist: flake8 >=3.8 ; extra == 'dev'
